trello/Trello.py
trello/__init__.py
trello.py-0.0.6.post4.dist-info/LICENSE
trello.py-0.0.6.post4.dist-info/METADATA
trello.py-0.0.6.post4.dist-info/WHEEL
trello.py-0.0.6.post4.dist-info/top_level.txt
trello.py-0.0.6.post4.dist-info/RECORD
