Metadata-Version: 2.1
Name: trello.py
Version: 0.0.6.post4
Summary: A simple and user-friendly Python to Trello API
Home-page: https://github.com/Batman212369/trello.py
Author: Batman212369
Author-email: batman212369.official@gmail.com
License: UNKNOWN
Platform: UNKNOWN
Classifier: Development Status :: 3 - Alpha
Classifier: Intended Audience :: Developers
Classifier: License :: OSI Approved :: MIT License
Classifier: Programming Language :: Python :: 3.6
Classifier: Programming Language :: Python :: 3.7
Classifier: Programming Language :: Python :: 3.8
Classifier: Operating System :: OS Independent
Requires-Python: >=3.6
Requires-Dist: requests
